{
  "$schema": "https://mintlify.com/schema.json",
  "name": "ZEBEDEE",
  "logo": {
    "dark": "/logo/light.png",
    "light": "/logo/dark.png"
  },
  "favicon": "/favicon.png",
  "colors": {
    "primary": "#9563FF",
    "light": "#AE87FF",
    "dark": "#0D001D",
    "background": {
      "dark": "#090014"
    },
    "anchors": {
      "from": "#FF7F57",
      "to": "#9563FF"
    }
  },
  "topbarLinks": [
    {
      "name": "Status",
      "url": "https://status.zebedee.io/"
    },
    {
      "name": "Blog",
      "url": "https://blog.zebedee.io/"
    },
    {
      "name": "GitHub",
      "url": "https://github.com/zebedeeio"
    }
  ],
  "topbarCtaButton": {
    "name": "Discord",
    "url": "https://discord.gg/zbd"
  },
  "tabs": [
    {
      "name": "API Reference",
      "url": "api"
    }
  ],
  "anchors": [],
  "navigation": [
    {
      "group": "Overview",
      "pages": ["docs/quick-start", "docs/lightning-network", "docs/glossary"]
    },
    {
      "group": "ZEBEDEE API",
      "pages": [
        "docs/zebedee-api/overview",
        "docs/zebedee-api/authentication",
        "docs/zebedee-api/error-handling",
        "docs/zebedee-api/sdks",
        "docs/zebedee-api/resources",
        {
          "group": "Payouts",
          "pages": [
            "docs/payouts/lightning-address",
            "docs/payouts/lightning-charges",
            "docs/payouts/withdrawal-requests",
            "docs/payouts/zbd-gamertag"
          ]
        },
        {
          "group": "Payins",
          "pages": ["docs/payins/charges", "docs/payins/zbd-gamertag"]
        }
      ]
    },
    {
      "group": "Guides",
      "pages": [
        {
          "group": "ZBD Login",
          "pages": [
            "docs/zbd-login/intro",
            "docs/zbd-login/building",
            "docs/zbd-login/design",
            "docs/zbd-login/walkthrough",
            "docs/zbd-login/advanced"
          ]
        },
        {
          "group": "Miscellaneous",
          "pages": [
            "docs/guides/nostr-relay",
            "docs/guides/lightning-address",
            "docs/guides/static-charges"
          ]
        },
        {
          "group": "Community",
          "pages": [
            "docs/guides/custom-lightning-address-app",
            "docs/guides/send-payment-to-ln-address-app"
          ]
        }
      ]
    },
    {
      "group": "Walkthroughs",
      "pages": [
        {
          "group": "Developer Dashboard",
          "pages": [
            "docs/dashboard/overview",
            {
              "group": "Account",
              "pages": [
                "docs/dashboard/signup",
                "docs/dashboard/complete-profile"
              ]
            },
            {
              "group": "Projects",
              "pages": [
                "docs/dashboard/projects/create",
                "docs/dashboard/projects/sandbox",
                "docs/dashboard/projects/edit",
                "docs/dashboard/projects/wallet",
                "docs/dashboard/projects/api",
                "docs/dashboard/projects/archive"
              ]
            },
            {
              "group": "Vouchers",
              "pages": ["docs/dashboard/vouchers"]
            }
          ]
        },
        {
          "group": "ZBD Shield",
          "pages": [
            "docs/zbd-shield/overview",
            "docs/zbd-shield/access",
            "docs/zbd-shield/apikey",
            "docs/zbd-shield/connect",
            "docs/zbd-shield/faq"
          ]
        },
        {
          "group": "ZBD App",
          "pages": [
            "docs/zbd-app/download",
            "docs/zbd-app/uri-schemes",
            "docs/zbd-app/wallet-limits"
          ]
        },
        {
          "group": "ZBD Streamer",
          "pages": [
            "docs/zbd-streamer/overview",
            "docs/zbd-streamer/customization"
          ]
        }
      ]
    },
    {
      "group": "API Documentation",
      "pages": ["api/introduction"]
    },
    {
      "group": "Charges",
      "pages": ["api/charges/create", "api/charges/get", "api/charges/decode"]
    },
    {
      "group": "Static Charges",
      "pages": [
        "api/static-charges/create",
        "api/static-charges/get",
        "api/static-charges/update"
      ]
    },
    {
      "group": "Payments",
      "pages": ["api/payments/send", "api/payments/get"]
    },
    {
      "group": "Lightning Address",
      "pages": [
        "api/lightning-address/send",
        "api/lightning-address/validate",
        "api/lightning-address/create"
      ]
    },
    {
      "group": "Keysend",
      "pages": ["api/keysend/send"]
    },
    {
      "group": "ZBD Gamertags",
      "pages": [
        "api/gamertag/send",
        "api/gamertag/get",
        "api/gamertag/create",
        "api/gamertag/get-user-id",
        "api/gamertag/get-gamertag"
      ]
    },
    {
      "group": "Wallet",
      "pages": ["api/wallet/get"]
    },
    {
      "group": "Utils",
      "pages": [
        "api/utils/btc-usd",
        "api/utils/is-supported-region",
        "api/utils/api"
      ]
    },
    {
      "group": "Internal Transfer",
      "pages": ["api/internal-transfer/create"]
    },
    {
      "group": "Withdrawal Requests",
      "pages": ["api/withdrawal-requests/create", "api/withdrawal-requests/get"]
    },
    {
      "group": "ZBD Login (OAuth2)",
      "pages": [
        "api/oauth2/authorization",
        "api/oauth2/fetch-access-token",
        "api/oauth2/refresh-token",
        "api/oauth2/get-user",
        "api/oauth2/get-wallet"
      ]
    },
    {
      "group": "Sandbox API",
      "pages": ["api/gamertag/send-gamertag"]
    }
  ],
  "footerSocials": {
    "twitter": "https://twitter.com/zebedeeio",
    "github": "https://github.com/zebedeeio",
    "discord": "https://discord.gg/zbd"
  }
}
